cridlib/__init__.py
cridlib/get.py
cridlib/lib.py
cridlib/parse.py
cridlib/py.typed
cridlib/strategy/__init__.py
cridlib/strategy/future.py
cridlib/strategy/now.py
cridlib/strategy/past.py
cridlib/util.py
rabe_cridlib-0.13.2.dist-info/METADATA
rabe_cridlib-0.13.2.dist-info/WHEEL
rabe_cridlib-0.13.2.dist-info/licenses/LICENSE
rabe_cridlib-0.13.2.dist-info/RECORD
