Metadata-Version: 2.4
Name: rabe-cridlib
Version: 0.13.2
Summary: Generate CRIDs for RaBe
License: AGPL-3
License-File: LICENSE
Author: RaBe IT-Reaktion
Author-email: it@rabe.ch
Requires-Python: >=3.11,<4.0
Classifier: Development Status :: 3 - Alpha
Classifier: Intended Audience :: Developers
Classifier: License :: Other/Proprietary License
Classifier: Programming Language :: Python :: 3
Classifier: Programming Language :: Python :: 3.11
Classifier: Programming Language :: Python :: 3.12
Classifier: Programming Language :: Python :: 3.13
Classifier: Programming Language :: Python :: 3.14
Classifier: Topic :: Multimedia :: Sound/Audio :: Conversion
Classifier: Topic :: Software Development :: Libraries :: Python Modules
Requires-Dist: python-slugify (>=8.0.0,<9.0.0)
Requires-Dist: pytz (>=2022.6)
Requires-Dist: requests (>=2.28.1,<3.0.0)
Requires-Dist: uritools (>=4,<7)
Project-URL: Repository, https://github.com/radiorabe/python-rabe-cridlib
